{
  "name": "trials",
  "title": "Trails through the Veillands",
  "description": "",
  "authors": [],
  "url": "https://github.com/Jwendling2150/trials",
  "flags": {},
  "version": "1.0.0",
  "scripts": [],
  "esmodules": [],
  "styles": [],
  "languages": [],
  "packs": [
    {
      "label": "Veilland Items",
      "type": "Item",
      "name": "veilland-items",
      "path": "packs/veilland-items.db",
      "system": "dnd5e",
      "package": "world",
      "entity": "Item",
      "private": false
    }
  ],
  "system": "dnd5e",
  "dependencies": [],
  "socket": false,
  "download": "https://github.com/Jwendling2150/trials/archive/refs/heads/main.zip",
  "protected": false,
  "background": "MistyCity.jpg",
  "coreVersion": "9.269",
  "resetKeys": false,
  "safeMode": false,
  "systemVersion": "1.6.3"
}